{
  "name": "Full-Stack (Vite + Express)",
  "description": "Monorepo with npm workspaces: run `npm install` then `npm run dev` from the repo root. Vite uses host 0.0.0.0 on 5173; Express listens on 4000. The browser only hits same-origin /api; Vite proxies to the backend.",
  "techStack": [
    "React",
    "TypeScript",
    "Vite",
    "Express",
    "Node"
  ],
  "level": "mid",
  "files": {
    "/.gitignore": "node_modules\ndist\n.DS_Store\n.env\n.env.local\n*.log\n",
    "/README.md": "# Full-stack assessment (Vite + API)\n\n## Layout\n\n- **Root** — one command runs Vite and the API via npm workspaces.\n- **frontend** — Vite on **5173**, `server.host: '0.0.0.0'` (required for host port mapping to the container).\n- **backend** — API on **4000**; keep it internal; the browser only talks to **5173** and Vite **proxies** `/api/*` → the backend.\n\n## Run\n\n```bash\nnpm install\nnpm run dev\n```\n\nYou should see both processes in one terminal. Open the **Preview** tab in the assessment UI (it points at your mapped **5173** port).\n\n## How API calls work in preview\n\n- Use **relative** URLs in the browser: `fetch('/api/health')`, not `http://localhost:4000/...`.\n- The browser talks to the same origin as the Vite page (**5173**). Vite forwards `/api` to `http://127.0.0.1:4000`.\n\n## If Preview is blank\n\n1. Confirm `npm run dev` is running and Vite printed “ready” on 5173.\n2. In this template, the backend must be up for `/api/health` to return 200 (check the terminal for “Backend listening on 4000”).\n3. Click **Reload** on the preview toolbar.\n\n## Seeded bugs (optional)\n\nDecide per assessment whether work is in `frontend/`, `backend/`, or both. For DB work, add scripts like `db:reset` to `package.json` and document them here.\n",
    "/backend/package.json": "{\n  \"name\": \"backend\",\n  \"private\": true,\n  \"type\": \"module\",\n  \"scripts\": {\n    \"dev\": \"tsx watch src/index.ts\"\n  },\n  \"dependencies\": {\n    \"express\": \"^4.18.2\"\n  },\n  \"devDependencies\": {\n    \"@types/express\": \"^4.17.21\",\n    \"tsx\": \"^4.7.0\",\n    \"typescript\": \"^5.3.0\"\n  }\n}\n",
    "/backend/src/index.ts": "import express from 'express'\n\nconst app = express()\nconst PORT = 4000\n\n// Only Vite (5173) is exposed in assessment preview; browser calls /api on same origin, Vite proxies here.\napp.get('/api/health', (_req, res) => {\n  res.json({ ok: true, service: 'assessment-api' })\n})\n\n// Example: extend with routes your assessment needs\napp.get('/api/users', (_req, res) => {\n  res.json({ data: [] })\n})\n\napp.use(express.json())\n\napp.listen(PORT, '0.0.0.0', () => {\n  console.log(`Backend listening on ${PORT}`)\n})\n",
    "/backend/tsconfig.json": "{\n  \"compilerOptions\": {\n    \"target\": \"ES2022\",\n    \"module\": \"NodeNext\",\n    \"moduleResolution\": \"NodeNext\",\n    \"strict\": true,\n    \"skipLibCheck\": true,\n    \"esModuleInterop\": true,\n    \"outDir\": \"dist\",\n    \"rootDir\": \"src\"\n  },\n  \"include\": [\"src\"]\n}\n",
    "/frontend/index.html": "<!DOCTYPE html>\n<html lang=\"en\">\n  <head>\n    <meta charset=\"UTF-8\" />\n    <meta name=\"viewport\" content=\"width=device-width, initial-scale=1.0\" />\n    <title>Assessment — Full-stack</title>\n  </head>\n  <body>\n    <div id=\"root\"></div>\n    <script type=\"module\" src=\"/src/main.tsx\"></script>\n  </body>\n</html>\n",
    "/frontend/package.json": "{\n  \"name\": \"frontend\",\n  \"private\": true,\n  \"type\": \"module\",\n  \"scripts\": {\n    \"dev\": \"vite\",\n    \"build\": \"vite build\",\n    \"preview\": \"vite preview\"\n  },\n  \"dependencies\": {\n    \"react\": \"^18.2.0\",\n    \"react-dom\": \"^18.2.0\"\n  },\n  \"devDependencies\": {\n    \"@types/react\": \"^18.2.0\",\n    \"@types/react-dom\": \"^18.2.0\",\n    \"@vitejs/plugin-react\": \"^4.2.1\",\n    \"typescript\": \"^5.3.0\",\n    \"vite\": \"^5.0.0\"\n  }\n}\n",
    "/frontend/src/App.tsx": "import { useEffect, useState } from 'react'\n\n/**\n * Use relative /api/* URLs so Vite's dev server proxies to the Express app on 4000.\n * Do not point the browser at http://localhost:4000 in assessment preview — only 5173 is exposed.\n */\nexport function App() {\n  const [status, setStatus] = useState<'loading' | 'ok' | 'error'>('loading')\n  const [message, setMessage] = useState<string>('')\n\n  useEffect(() => {\n    let cancelled = false\n    ;(async () => {\n      try {\n        const r = await fetch('/api/health')\n        const j = (await r.json().catch(() => ({}))) as { ok?: boolean }\n        if (cancelled) return\n        if (r.ok && j?.ok) {\n          setStatus('ok')\n          setMessage('API reachable via Vite proxy.')\n        } else {\n          setStatus('error')\n          setMessage(`HTTP ${r.status}`)\n        }\n      } catch (e) {\n        if (cancelled) return\n        setStatus('error')\n        setMessage(e instanceof Error ? e.message : 'Request failed')\n      }\n    })()\n    return () => {\n      cancelled = true\n    }\n  }, [])\n\n  return (\n    <main>\n      <h1>Full-stack template</h1>\n      <p>\n        {status === 'loading' && 'Checking /api/health…'}\n        {status === 'ok' && <span style={{ color: 'green' }}>{message}</span>}\n        {status === 'error' && (\n          <span style={{ color: 'crimson' }}>\n            {message} — run <code>npm run dev</code> from the repo root (Vite + API), then use Preview →\n            Reload.\n          </span>\n        )}\n      </p>\n    </main>\n  )\n}\n",
    "/frontend/src/index.css": "* {\n  box-sizing: border-box;\n}\nbody {\n  margin: 0;\n  font-family: system-ui, sans-serif;\n  line-height: 1.5;\n  padding: 1.5rem;\n}\n",
    "/frontend/src/main.tsx": "import React from 'react'\nimport ReactDOM from 'react-dom/client'\nimport { App } from './App'\nimport './index.css'\n\nReactDOM.createRoot(document.getElementById('root')!).render(\n  <React.StrictMode>\n    <App />\n  </React.StrictMode>\n)\n",
    "/frontend/src/vite-env.d.ts": "/// <reference types=\"vite/client\" />\n",
    "/frontend/tsconfig.json": "{\n  \"compilerOptions\": {\n    \"target\": \"ES2020\",\n    \"useDefineForClassFields\": true,\n    \"lib\": [\"ES2020\", \"DOM\", \"DOM.Iterable\"],\n    \"module\": \"ESNext\",\n    \"skipLibCheck\": true,\n    \"moduleResolution\": \"bundler\",\n    \"allowImportingTsExtensions\": true,\n    \"isolatedModules\": true,\n    \"moduleDetection\": \"force\",\n    \"noEmit\": true,\n    \"jsx\": \"react-jsx\",\n    \"strict\": true,\n    \"noUnusedLocals\": true,\n    \"noUnusedParameters\": true,\n    \"noFallthroughCasesInSwitch\": true\n  },\n  \"include\": [\"src\"]\n}\n",
    "/frontend/vite.config.ts": "import { defineConfig } from 'vite'\nimport react from '@vitejs/plugin-react'\n\n// HMR routing through code-server's /proxy/{port}/ tunnel.\n//\n// PROMORA_IDE_HOST_PORT  — the host port for code-server (e.g. 18082).\n//   HMR WebSocket goes:  browser → ws://localhost:<ide> → code-server → /proxy/5173/ → Vite.\n//\n// PROMORA_PREVIEW_HOST_PORT — the host port mapped directly to :5173.\n//   Used as fallback if IDE port is not available.\nconst idePort     = process.env.PROMORA_IDE_HOST_PORT\n  ? Number(process.env.PROMORA_IDE_HOST_PORT)\n  : undefined\nconst previewPort = process.env.PROMORA_PREVIEW_HOST_PORT\n  ? Number(process.env.PROMORA_PREVIEW_HOST_PORT)\n  : undefined\n\nfunction hmrConfig() {\n  if (idePort) {\n    // Route HMR WebSocket through code-server proxy — same path as the preview iframe\n    return { host: 'localhost', clientPort: idePort, path: '/proxy/5173/', protocol: 'ws' as const }\n  }\n  if (previewPort) {\n    // Route HMR WebSocket through the directly-mapped port\n    return { host: 'localhost', clientPort: previewPort, protocol: 'ws' as const }\n  }\n  // Local dev without Docker — HMR on same host/port\n  return true\n}\n\nexport default defineConfig({\n  plugins: [react()],\n  server: {\n    port: 5173,\n    host: '0.0.0.0',\n    strictPort: true,\n    hmr: hmrConfig(),\n    proxy: {\n      '/api': {\n        target: 'http://127.0.0.1:4000',\n        changeOrigin: true,\n      },\n    },\n  },\n})\n",
    "/package.json": "{\n  \"name\": \"assessment-fullstack\",\n  \"private\": true,\n  \"workspaces\": [\n    \"frontend\",\n    \"backend\"\n  ],\n  \"scripts\": {\n    \"dev\": \"concurrently -n f,b -c blue,green \\\"npm run dev -w frontend\\\" \\\"npm run dev -w backend\\\"\"\n  },\n  \"devDependencies\": {\n    \"concurrently\": \"^8.2.2\"\n  }\n}\n"
  }
}
